{"assets/fonts/Gaegu-Bold.ttf":["assets/fonts/Gaegu-Bold.ttf"],"assets/fonts/Gaegu-Light.ttf":["assets/fonts/Gaegu-Light.ttf"],"assets/fonts/Gaegu-Regular.ttf":["assets/fonts/Gaegu-Regular.ttf"],"assets/fonts/Pretendard-Black.otf":["assets/fonts/Pretendard-Black.otf"],"assets/fonts/Pretendard-Bold.otf":["assets/fonts/Pretendard-Bold.otf"],"assets/fonts/Pretendard-ExtraBold.otf":["assets/fonts/Pretendard-ExtraBold.otf"],"assets/fonts/Pretendard-ExtraLight.otf":["assets/fonts/Pretendard-ExtraLight.otf"],"assets/fonts/Pretendard-Light.otf":["assets/fonts/Pretendard-Light.otf"],"assets/fonts/Pretendard-Medium.otf":["assets/fonts/Pretendard-Medium.otf"],"assets/fonts/Pretendard-Regular.otf":["assets/fonts/Pretendard-Regular.otf"],"assets/fonts/Pretendard-SemiBold.otf":["assets/fonts/Pretendard-SemiBold.otf"],"assets/fonts/Pretendard-Thin.otf":["assets/fonts/Pretendard-Thin.otf"],"assets/icons/Custom_Icons1.ttf":["assets/icons/Custom_Icons1.ttf"],"assets/icons/Custom_Icons2.ttf":["assets/icons/Custom_Icons2.ttf"],"assets/icons/edit.ttf":["assets/icons/edit.ttf"],"assets/images/감스트-gamst.gif":["assets/images/감스트-gamst.gif"],"assets/images/뚱이.webp":["assets/images/뚱이.webp"],"assets/images/심슨.gif":["assets/images/심슨.gif"],"assets/images/우주.mp4":["assets/images/우주.mp4"],"assets/images/은채.jpeg":["assets/images/은채.jpeg"],"assets/images/facebook-logo.png":["assets/images/facebook-logo.png"],"assets/images/google-logo.png":["assets/images/google-logo.png"],"assets/images/kakao.png":["assets/images/kakao.png"],"assets/images/rocket.png":["assets/images/rocket.png"],"assets/video/새.mp4":["assets/video/새.mp4"],"packages/cupertino_icons/assets/CupertinoIcons.ttf":["packages/cupertino_icons/assets/CupertinoIcons.ttf"]}